{"language":"en","daily_theater_id":1000744,"year":2022,"month":2,"day":15,"title":"Happy Birthday, Lanzhu-senpai!","detail_text":"\u003c:th_ch0211/\u003eFufufu~♪ Perfect timing, Kasumi! Here. Lanzhu will hold a birthday party today, so make sure to come to the place written on there after our club activities♪\u003c:dt_line_end/\u003e\u003c:th_ch0202/\u003eEh!? But we were already organizing your birthday party ourselves....\u003c:dt_line_end/\u003e\u003c:th_ch0211/\u003eEh!? It’s my birthday, so it’s obvious Lanzhu should be the one to invite and show you my hospitality, right?\u003c:dt_line_end/\u003e\u003c:th_ch0202/\u003eNo way!! We are the ones supposed to secretly organize a party and surprise you!\u003c:dt_line_end/\u003e\u003c:th_ch0211/\u003eEeeeh!? Is that really okay!?\u003c:dt_line_end/\u003e\u003c:th_ch0202/\u003eOf course it is!! We’ve been preparing for this for a week. Nico-senpai will also bring looots of fried chicken just for you since you love those so much!\u003c:dt_line_end/\u003e\u003c:th_ch0211/\u003eLanzhu can’t believe this is actually happening! My heart is overwhelmed with gratitude. Lanzhu might pass out!! And.... and Lanzhu can’t believe that Nico made those fried chicken just for me....\u003c:dt_line_end/\u003e\u003c:th_ch0202/\u003eKanata-senpai, Emma-senpai and Ayumu-senpai made a lot of food just for you, too. And guess what? Kasumin also made my special buns! Come on, Lanzhu-senpai, we’re going to the party. Let’s go~!\u003c:dt_line_end/\u003e\u003c:th_ch0211/\u003eKyaaa! Okay! Lanzhu will go! Then Lanzhu will treat my party as a way to thank all of you! We’ll have a party after the party!\u003c:dt_line_end/\u003e\u003c:th_ch0202/\u003eBut make sure to enjoy our party first, okay? Happy birthday, Lanzhu-senpai!\u003c:dt_line_end/\u003e\u003c:th_ch0000/\u003eTranslated by SIFAStheatre and Idol Story\u003c:dt_line_end/\u003e"}