{"language":"en","daily_theater_id":1000871,"year":2022,"month":6,"day":22,"title":"Wild Hanpen","detail_text":"\u003c:th_ch0005/\u003eTORYAAAH! URYAAAH!\u003c:dt_line_end/\u003e\u003c:th_ch0209/\u003eW-, wow....\u003c:dt_line_end/\u003e\u003c:th_ch0005/\u003eRin is not done yet~! YOISHOOO!!\u003c:dt_line_end/\u003e\u003c:th_ch5206/\u003eNnyaaaaaah!\u003c:dt_line_end/\u003e\u003c:th_ch0209/\u003eI’ve never seen Hanpen like this before. Rina-chan’s board「Spinning」\u003c:dt_line_end/\u003e\u003c:th_ch0005/\u003eAlright! Good girl, Hanpen! There there! You were really agile, and your movements were so sharp!\u003c:dt_line_end/\u003e\u003c:th_ch0209/\u003eR-, Rin-chan!!\u003c:dt_line_end/\u003e\u003c:th_ch0005/\u003eHm?\u003c:dt_line_end/\u003e\u003c:th_ch0209/\u003eI didn’t realize until now.... how amazing Hanpen is. How I played with her wasn’t able to draw her true potential. From now on, I want to do more active plays with her. So please, can you.... teach me how to play with Hanpen! Rina-chan’s board「Bow」\u003c:dt_line_end/\u003e\u003c:th_ch0005/\u003eIs that so? Rin doesn’t really understand, but.... leave it to me nya!\u003c:dt_line_end/\u003e\u003c:th_ch0000/\u003eTranslated by SIFAStheatre and Idol Story\u003c:dt_line_end/\u003e"}