{"language":"en","daily_theater_id":1001141,"year":2023,"month":3,"day":19,"title":"QU4RTZ Live - Day 2!","detail_text":"\u003c:th_ch0202/\u003eYesterday’s concert was so awesome......\u003c:dt_line_end/\u003e\u003c:th_ch0206/\u003eIt’s all thanks to QU4RTZ’s leader, Kasumi-chan~\u003c:dt_line_end/\u003e\u003c:th_ch0209/\u003eMhmm. Kasumi-chan, you’re so reliable.\u003c:dt_line_end/\u003e\u003c:th_ch0208/\u003eYeah! I think so, too~\u003c:dt_line_end/\u003e\u003c:th_ch0202/\u003eHuh......? No, there were some moments when Kasumin relied on Kanata-senpai and Emma-senpai and Rinako, too.\u003c:dt_line_end/\u003e\u003c:th_ch0206/\u003eOooh, really? I’m happy to hear that.\u003c:dt_line_end/\u003e\u003c:th_ch0209/\u003eThat’s embarrassing. Rina-chan Board says, “Blush.”\u003c:dt_line_end/\u003e\u003c:th_ch0202/\u003eI guess, umm...... Everybody was leading QU4RTZ? But isn’t that kinda weird...?\u003c:dt_line_end/\u003e\u003c:th_ch0208/\u003eThen, should I lead QU4RTZ for a change...?\u003c:dt_line_end/\u003e\u003c:th_ch0202/\u003eLet’s just keep having everyone lead QU4RTZ!\u003c:dt_line_end/\u003e\u003c:th_ch0000/\u003eTranslated by SIFAStheatre and Idol Story\u003c:dt_line_end/\u003e"}