{"language":"en","daily_theater_id":1000265,"year":2020,"month":10,"day":24,"title":"Change Into a Black Cat!","detail_text":"\u003c:th_ch0003/\u003eRin-chan, have you decided on what you will wear for the Halloween party?\u003c:dt_line_end/\u003e\u003c:th_ch0005/\u003eRin will dress up as a ghost!\u003c:dt_line_end/\u003e\u003c:th_ch0003/\u003eIs that so, I was wondering if you would be a black cat or something like that\u003c:dt_line_end/\u003e\u003c:th_ch0005/\u003eEh?\u003c:dt_line_end/\u003e\u003c:th_ch0003/\u003eSee, you love cats, right, Rin-chan?\u003c:dt_line_end/\u003e\u003c:th_ch0005/\u003eA black cat.... It’s cute, but.... Rin will probably be a ghost!\u003c:dt_line_end/\u003e\u003c:th_ch0003/\u003eI see.... I brought black cat ears that I used for my part-time job at the maid store though.... I think they will really suit you though, Rin-chan....\u003c:dt_line_end/\u003e\u003c:th_ch0005/\u003eEh!? Is that so? C-, can Rin try them a little bit?\u003c:dt_line_end/\u003e\u003c:th_ch0003/\u003eYou’ll wear them!? I’m so happy! Then, stay put for a little bit, okay~ ....There, it’s on. I think it really suits you and looks really cute, Rin-chan! I’ll be happy if you wear them. Can’t you dress up as both a ghost and a black cat....?\u003c:dt_line_end/\u003e\u003c:th_ch0005/\u003e....Rin wants to try dressing up as a black cat too nya-!\u003c:dt_line_end/\u003e\u003c:th_ch0000/\u003eTranslated by SIFAStheatre and Idol Story\u003c:dt_line_end/\u003e"}