{"language":"en","daily_theater_id":1000739,"year":2022,"month":2,"day":10,"title":"Happy Birthday, Kanan-chan!","detail_text":"\u003c:th_ch0103/\u003eAhh~, that was fun! Thank you so much for today, Ruby-chan!\u003c:dt_line_end/\u003e\u003c:th_ch0109/\u003eEhehe, Ruby is glad you’re happy! It was worth all the effort everyone put together.\u003c:dt_line_end/\u003e\u003c:th_ch0103/\u003eBut that was hilarious~! I went today expecting a birthday cake, but it was a birthday pizza instead! I’ve never seen one before!\u003c:dt_line_end/\u003e\u003c:th_ch0109/\u003eWe had trouble with the pizza. Drawing the shape of the letters with vegetables and ketchup was really hard.\u003c:dt_line_end/\u003e\u003c:th_ch0103/\u003eI’m truly thankful for everything. So, where are we going now? Everyone’s gone home, you know?\u003c:dt_line_end/\u003e\u003c:th_ch0109/\u003eDo you want to visit the observatory for a bit? It would be great to go watch the starry sky on your birthday, Kanan-chan. Then Ruby wants to wish you a happy birthday again there.\u003c:dt_line_end/\u003e\u003c:th_ch0103/\u003eThat sounds good, let’s go!\u003c:dt_line_end/\u003e\u003c:th_ch0109/\u003eEhehe, it’s gonna be fun~\u003c:dt_line_end/\u003e\u003c:th_ch0103/\u003e....Ah, I see, so that’s it. When we get there, everyone will-....\u003c:dt_line_end/\u003e\u003c:th_ch0109/\u003eAaaah~! No, stop! You can’t say it even if you know! We were going to surprise you one more-.... Pigii!?!? Ruby said it....\u003c:dt_line_end/\u003e\u003c:th_ch0103/\u003eFufu, guess I got it right~♪ Ah, I’ve got an idea. Why don’t we be the ones to surprise them instead? Lend me your ears, Ruby-chan. You see.... *Whisper Whisper*.....\u003c:dt_line_end/\u003e\u003c:th_ch0109/\u003eW-, wow!! That sounds interesting~!!\u003c:dt_line_end/\u003e\u003c:th_ch0000/\u003eTranslated by SIFAStheatre and Idol Story\u003c:dt_line_end/\u003e"}