{"language":"ja","daily_theater_id":1000852,"year":2022,"month":6,"day":3,"title":"凛が！！","detail_text":"\u003c:th_ch0005/\u003e海未ちゃーん！海未ちゃん海未ちゃん！\u003c:dt_line_end/\u003e\u003c:th_ch0004/\u003eどうしたのですか、凛？\u003c:dt_line_end/\u003e\u003c:th_ch0005/\u003eあのね、凛とダンスの練習しよ！\u003c:dt_line_end/\u003e\u003c:th_ch0004/\u003eもちろんいいですが、急にどうしたんですか？\u003c:dt_line_end/\u003e\u003c:th_ch0005/\u003eかよちんがね、この間海未ちゃんに朝練付き合ってもらって、苦手だったステップのコツが掴めた、って言ってたの。凛もかよちんと一緒に練習したかったにゃ……\u003c:dt_line_end/\u003e\u003c:th_ch0004/\u003eああ……そういえば、こっそり朝練をしようとしてた花陽に付き合ったことがありました\u003c:dt_line_end/\u003e\u003c:th_ch0005/\u003eもっと凛がかよちんに上手に教えてあげられたらよかったのに～、って悔しいの！\u003c:dt_line_end/\u003e\u003c:th_ch0004/\u003eそうでしたか……\u003c:dt_line_end/\u003e\u003c:th_ch0005/\u003eだからね、海未ちゃん。上手に教えてあげられるやり方を教えて！\u003c:dt_line_end/\u003e\u003c:th_ch0004/\u003eわかりました！ふふっ、凛は花陽のことが大好きですね\u003c:dt_line_end/\u003e"}