{"language":"ja","daily_theater_id":1000226,"year":2020,"month":9,"day":15,"title":"ふさわしい舞台！","detail_text":"\u003c:th_ch0009/\u003e鞠莉、この間、穂乃果を一瞬にして山に攫ったんですって？\u003c:dt_line_end/\u003e\u003c:th_ch0108/\u003eワッツ？　高原に遊びに行ったときのことかしら？\u003c:dt_line_end/\u003e\u003c:th_ch0009/\u003eたぶんそれね。穂乃果、すっごく楽しかったらしくて、\u003c:br_inline/\u003eヘリがいかに早かったか、毎日聞かされるのよ\u003c:dt_line_end/\u003e\u003c:th_ch0108/\u003eワオ、喜んでもらえたなら嬉しいわ。\u003c:br_inline/\u003eマリーもすっごく楽しかったから♪ 　にこっちも乗る？\u003c:dt_line_end/\u003e\u003c:th_ch0009/\u003eふっふっふ……その言葉を待ってたわ。\u003c:br_inline/\u003eでも！　この、大銀河宇宙ナンバーワンスクールアイドルであるにこにーは、\u003c:br_inline/\u003eヘリをステージの演出として使いたいのよ！！\u003c:dt_line_end/\u003e\u003c:th_ch0108/\u003e演出に？　壮大ねえ～。でも、おもしろそう！\u003c:br_inline/\u003eどう使いたいの？\u003c:dt_line_end/\u003e\u003c:th_ch0009/\u003eえっと、それはまだ考え中だけど、\u003c:br_inline/\u003e例えばにこがヘリから降りてきたり、ヘリから紙吹雪を降らせたり……\u003c:dt_line_end/\u003e\u003c:th_ch0108/\u003eん～、せっかくヘリを使うなら、４機使ってステージそのものを\u003c:br_inline/\u003eヘリで空中に持ち上げちゃうっていうのはどう？　うん、我ながらナイスアイディア！\u003c:br_inline/\u003e安全に関しては考えなきゃだけど、そのくらいやらなきゃ面白くないわ～！！\u003c:dt_line_end/\u003e\u003c:th_ch0009/\u003eは！？　ステージを持ち上げる！？\u003c:br_inline/\u003eちょっと、なにもそこまで……にこだって求めてないわよ……？\u003c:dt_line_end/\u003e\u003c:th_ch0108/\u003eノーノー！　大銀河宇宙ナンバーワンにふさわしいステージにするなら、\u003c:br_inline/\u003eこのくらいしなきゃダメよ。\u003c:br_inline/\u003e私、４機用意できるか確認してくるわ。ちょっと待ってて～\u003c:dt_line_end/\u003e\u003c:th_ch0009/\u003e待ってよ、さすがに空中はないわよ！\u003c:br_inline/\u003eちょっと！　鞠莉！　鞠莉ーーーー！？\u003c:dt_line_end/\u003e"}