{"language":"ja","daily_theater_id":1000466,"year":2021,"month":5,"day":13,"title":"最果て知らずのストーリー","detail_text":"\u003c:th_ch0203/\u003e……と、このような感じで、善子さんとの掛け合いのお芝居をしたんです\u003c:dt_line_end/\u003e\u003c:th_ch0001/\u003eすごい！　すごいね、しずくちゃん！\u003c:br_inline/\u003e私、天使のイメージ変わっちゃったかも～。\u003c:br_inline/\u003e天使ってただ優しいだけじゃないんだ……。\u003c:br_inline/\u003e堕天使の善子ちゃんを思うあまりの突き放すようなセリフ……！\u003c:br_inline/\u003eかっこよかったよ～～～！！\u003c:dt_line_end/\u003e\u003c:th_ch0203/\u003eえへへへっ。そ、そんなに褒められると照れます。\u003c:br_inline/\u003eそれに、この台本はいろんな方に手伝ってもらってできたものです。\u003c:br_inline/\u003e海未さんの力も借りました\u003c:dt_line_end/\u003e\u003c:th_ch0001/\u003eえっ！？　海未ちゃんそんなこと一言もいってなかったよ～！\u003c:br_inline/\u003e私もやってみたい～！\u003c:dt_line_end/\u003e\u003c:th_ch0203/\u003e本当ですか！？　穂乃果さんのお芝居、私も見てみたいです！\u003c:dt_line_end/\u003e\u003c:th_ch0001/\u003e私がやるんだったら、どんな役がいいと思う？\u003c:dt_line_end/\u003e\u003c:th_ch0203/\u003eそうですねえ……穂乃果さんは天使側と堕天使側、どちらがいいですか？\u003c:dt_line_end/\u003e\u003c:th_ch0001/\u003eうっ……それは難しい質問だな～。\u003c:br_inline/\u003eどっちも魅力的だし、どっちとも友達になりたいよ～\u003c:dt_line_end/\u003e\u003c:th_ch0203/\u003eでしたら、海未さんに相談しましょうか\u003c:dt_line_end/\u003e\u003c:th_ch0001/\u003eそうだね、そうしよう！\u003c:br_inline/\u003eことりちゃんと海未ちゃんの役も作ってもらおう～！\u003c:dt_line_end/\u003e"}