{"language":"ja","daily_theater_id":1001046,"year":2022,"month":12,"day":14,"title":"不意打ち！？","detail_text":"\u003c:th_ch0002/\u003eどこにやったかしら……この辺りにしまったと思うんだけど……\u003c:dt_line_end/\u003e\u003c:th_ch0009/\u003e絵里、ちょっといい？\u003c:dt_line_end/\u003e\u003c:th_ch0002/\u003eうーん、ないわね……。じゃあここ？\u003c:dt_line_end/\u003e\u003c:th_ch0009/\u003eねえってば\u003c:dt_line_end/\u003e\u003c:th_ch0002/\u003eここにもないの！？じゃあ……\u003c:dt_line_end/\u003e\u003c:th_ch0009/\u003e絵里！！！\u003c:dt_line_end/\u003e\u003c:th_ch0002/\u003eきゃあっ！？\u003c:dt_line_end/\u003e\u003c:th_ch0009/\u003eうわあっ！？\u003c:dt_line_end/\u003e\u003c:th_ch0002/\u003e……なんでにこがそんなに驚いてるのよ？\u003c:dt_line_end/\u003e\u003c:th_ch0009/\u003e絵里が驚きすぎるからよ！ さっきから呼んでたのよ\u003c:dt_line_end/\u003e\u003c:th_ch0002/\u003eえ、そうだったの？ごめん、気がつかなかったわ。それで、なに？\u003c:dt_line_end/\u003e\u003c:th_ch0009/\u003e……えっと\u003c:dt_line_end/\u003e\u003c:th_ch0002/\u003e？\u003c:dt_line_end/\u003e\u003c:th_ch0009/\u003eびっくりしすぎて忘れちゃった……\u003c:dt_line_end/\u003e\u003c:th_ch0002/\u003e……じゃあ思い出すまで書類探しを手伝ってくれない？\u003c:dt_line_end/\u003e\u003c:th_ch0009/\u003eえー！？\u003c:dt_line_end/\u003e\u003c:th_ch0002/\u003eにこが早く思い出せばいいのよ。ほらほら、体育館使用の申請書、探して！\u003c:dt_line_end/\u003e"}