{"language":"ja","daily_theater_id":1000330,"year":2020,"month":12,"day":28,"title":"年末の忘れ物？","detail_text":"\u003c:th_ch0003/\u003eなんとか買えてよかったね～\u003c:dt_line_end/\u003e\u003c:th_ch0210/\u003eはい、これがないとお正月を迎えられませんから\u003c:dt_line_end/\u003e\u003c:th_ch0003/\u003e栞子ちゃんのおうちは、大掃除もう終わったの？\u003c:dt_line_end/\u003e\u003c:th_ch0210/\u003eええ。うちは12月に入ったら少しずつ進めて、\u003c:br_inline/\u003eクリスマス前には終わらせるんです\u003c:dt_line_end/\u003e\u003c:th_ch0003/\u003eそっか。じゃあ、ちょっとなら寄り道しても大丈夫だよね？\u003c:dt_line_end/\u003e\u003c:th_ch0210/\u003e寄り道……？\u003c:dt_line_end/\u003e\u003c:th_ch0003/\u003e希ちゃんがお手伝いしてる神社のそばに、\u003c:br_inline/\u003eとってもおいしい甘酒を出してるお店があるの。どうかな？\u003c:dt_line_end/\u003e\u003c:th_ch0210/\u003e甘酒！　大好きです！　行きたいです！\u003c:dt_line_end/\u003e\u003c:th_ch0003/\u003eふふっ、よかったあ。寒いから、あったまりに行こうね\u003c:dt_line_end/\u003e\u003c:th_ch0210/\u003eはい！\u003c:dt_line_end/\u003e"}