{"language":"ja","daily_theater_id":1000724,"year":2022,"month":1,"day":26,"title":"風邪撃退メニュー！","detail_text":"\u003c:th_ch0208/\u003e千歌ちゃーん！見て見て、これ！\u003c:dt_line_end/\u003e\u003c:th_ch0101/\u003eわあ！みかんのサンドイッチだー！\u003c:dt_line_end/\u003e\u003c:th_ch0208/\u003e千歌ちゃん、みかんを食べてれば風邪ひかない、って教えてくれたでしょ？だから、ごはんでもみかんを食べられるといいかなと思って作ってみたんだ～\u003c:dt_line_end/\u003e\u003c:th_ch0101/\u003eすごいすごーい！食べてもいい？\u003c:dt_line_end/\u003e\u003c:th_ch0208/\u003eもちろん！召し上がれ♪\u003c:dt_line_end/\u003e\u003c:th_ch0101/\u003eはむっ……んん～、最高～～～！\u003c:dt_line_end/\u003e\u003c:th_ch0208/\u003eふふっ、よかった♪でもサンドイッチ以外どうやってみかんをごはんとして食べたらいいかわからないんだあ。ずっとサンドイッチじゃ飽きちゃうかもしれないし\u003c:dt_line_end/\u003e\u003c:th_ch0101/\u003eふっふっふ～。私に任せて！みかんはね、鍋とかラーメンとかにも使えるんだよ～！\u003c:dt_line_end/\u003e\u003c:th_ch0208/\u003eえっ、そうなの！？\u003c:dt_line_end/\u003e\u003c:th_ch0101/\u003eサンドイッチのお礼にご馳走しちゃう！そうと決まれば早速行こ～\u003c:dt_line_end/\u003e"}