{"language":"ja","daily_theater_id":1000897,"year":2022,"month":7,"day":18,"title":"海の日","detail_text":"\u003c:th_ch0105/\u003eいや〜、泳いだ泳いだ！\u003c:dt_line_end/\u003e\u003c:th_ch0103/\u003eこんなに泳いだの久しぶりだね〜。早朝に曜が来たときは何事かと思ったけど\u003c:dt_line_end/\u003e\u003c:th_ch0105/\u003eだって今日って海の日でしょ？ 目一杯泳ぎたくてさ〜\u003c:dt_line_end/\u003e\u003c:th_ch0103/\u003e私なら付き合うと思ったの？\u003c:dt_line_end/\u003e\u003c:th_ch0105/\u003eうん！ 予想通りだった！\u003c:dt_line_end/\u003e\u003c:th_ch0103/\u003eまったくもう、この子は……\u003c:dt_line_end/\u003e\u003c:th_ch0105/\u003eかわいい幼なじみのお願い、聞いてくれてありがとね、果南ちゃん♪\u003c:dt_line_end/\u003e\u003c:th_ch0103/\u003eちゃっきりしてるなあ。でもま、かわいい幼なじみだからね。じゃあついでに、かわいい幼なじみにかき氷でも作ってあげよっか\u003c:dt_line_end/\u003e\u003c:th_ch0105/\u003eやったー！ シロップ何にしようかなあ？\u003c:dt_line_end/\u003e\u003c:th_ch0103/\u003e何種類でもかけていいよ♪ 今日は特別！\u003c:dt_line_end/\u003e"}