{"language":"ja","daily_theater_id":1000040,"year":2020,"month":3,"day":13,"title":"Don't stop!","detail_text":"\u003c:th_ch0001/\u003eあ・い・ちゃ～ん！　ちょっと耳貸して！\u003c:dt_line_end/\u003e\u003c:th_ch0205/\u003eなになに？　その顔はなんか企んでる顔だな～？\u003c:dt_line_end/\u003e\u003c:th_ch0001/\u003eこしょこしょ……こしょこしょ……。ね？　どう？\u003c:dt_line_end/\u003e\u003c:th_ch0205/\u003eまーーーじで！？　やるしかないじゃん！！\u003c:dt_line_end/\u003e\u003c:th_ch0001/\u003eでしょでしょ？　でも海未ちゃんが、もう少しちゃんと計画しないと危ない、って……\u003c:dt_line_end/\u003e\u003c:th_ch0205/\u003eあー……。うん、それはたしかに海未が正しい。うちのしずくもたぶんそう言う……\u003c:dt_line_end/\u003e\u003c:th_ch0001/\u003eでもでもぉ～！　愛ちゃんはじっとしてられる！？\u003c:dt_line_end/\u003e\u003c:th_ch0205/\u003eできん！！！　よーっしゃ、穂乃果！　アタシたちは前に進むのみ！！　叱られるときは一緒だ！！\u003c:dt_line_end/\u003e\u003c:th_ch0001/\u003eやったー！　愛ちゃんならそう言ってくれると思った！　二人で怒られるなら怖くないもんね！\u003c:dt_line_end/\u003e\u003c:th_ch0205/\u003eいっくぞー！\u003c:dt_line_end/\u003e"}