{"language":"ja","daily_theater_id":1000779,"year":2022,"month":3,"day":22,"title":"目標に向かって針路をとれ！","detail_text":"\u003c:th_ch0001/\u003eえ～と、確かこっちだったような……\u003c:dt_line_end/\u003e\u003c:th_ch0003/\u003e穂乃果ちゃん、どこに連れて行ってくれようとしてるの？\u003c:dt_line_end/\u003e\u003c:th_ch0001/\u003e果林さんに教えてもらったセレクトショップ！かわいいお洋服がたくさんあって、しかも安いの！\u003c:dt_line_end/\u003e\u003c:th_ch0106/\u003eあっ、私もそこ連れて行ってもらったことがあるわ。穂乃果、ショップの場所わかるの？私も行きた～い！\u003c:dt_line_end/\u003e\u003c:th_ch0102/\u003eふたりがそんなに行きたがるなんて、私も興味あるな\u003c:dt_line_end/\u003e\u003c:th_ch0001/\u003eえへへ。ことりちゃんも梨子ちゃんも絶対気に入るよ～。あ、思い出した！ここを曲がるんだよ！行こう～！\u003c:dt_line_end/\u003e\u003c:th_ch0106/\u003e私もこの辺見覚えあるような気がする！\u003c:dt_line_end/\u003e\u003c:th_ch0003/\u003eあっ、ふたりとも待って、走らなくても……！\u003c:dt_line_end/\u003e\u003c:th_ch0102/\u003e追いかけよう、ことりちゃん！\u003c:dt_line_end/\u003e\u003c:th_ch0003/\u003eショッピングに来たのにトレーニングみたいになっちゃってるよお～！\u003c:dt_line_end/\u003e"}