{"language":"ja","daily_theater_id":1000970,"year":2022,"month":9,"day":29,"title":"招き猫の日","detail_text":"\u003c:th_ch0002/\u003e招き猫の日……？ そんな日があるなんて知らなかったわ\u003c:dt_line_end/\u003e\u003c:th_ch0210/\u003e私も最近まで知りませんでした。 でもはんぺんが来てから猫について調べることが増えまして……\u003c:dt_line_end/\u003e\u003c:th_ch0002/\u003eふふっ、そうだったのね。それで、これからどこに連れて行ってくれるの？\u003c:dt_line_end/\u003e\u003c:th_ch0210/\u003e招き猫をお祀りしているお寺です。あるお殿様が、鷹狩りの帰りに通りかかったお寺の門前にいた猫に手招きされて立ち寄ったら雷雨を免れた……という由来があるそうですよ\u003c:dt_line_end/\u003e\u003c:th_ch0002/\u003eそんなお寺があるのね\u003c:dt_line_end/\u003e\u003c:th_ch0210/\u003eそこでいただける真っ白な招き猫がはんぺんに似ているので、部室に飾りたくて……\u003c:dt_line_end/\u003e\u003c:th_ch0002/\u003eいいわね。うちの部室も飾ろうかしら\u003c:dt_line_end/\u003e\u003c:th_ch0210/\u003eはい、ぜひ！ ここの招き猫は小判を持たず右手を上げているんだそうです。これは「緑」をもたらすことを意味しているのだとか\u003c:dt_line_end/\u003e\u003c:th_ch0002/\u003eへえ、興味深いわね。私がµ’sと出会えた緑、ニジガクやAqoursのみんな、いつも応援してくれるみんなと出会えた緑みたいに、これからもいろんな緑を結んでいきたいわ\u003c:dt_line_end/\u003e\u003c:th_ch0210/\u003eそうですね。今ある緑も、もっともっと強く結びたいです！\u003c:dt_line_end/\u003e"}