{"language":"ja","daily_theater_id":1001211,"year":2023,"month":5,"day":28,"title":"わいわいわい！","detail_text":"\u003c:th_ch0109/\u003e今日のイベント緊張する～！\u003c:dt_line_end/\u003e\u003c:th_ch0106/\u003eくっくっく……。その緊張、振り払ってあげましょうか？ 堕天使に伝わるこの秘密の薬で……\u003c:dt_line_end/\u003e\u003c:th_ch0105/\u003eあ、ちょーだい。はむっ……\u003c:dt_line_end/\u003e\u003c:th_ch0106/\u003eあー！\u003c:dt_line_end/\u003e\u003c:th_ch0105/\u003eおいしいのど飴だなあ～\u003c:dt_line_end/\u003e\u003c:th_ch0106/\u003eのど飴じゃないわよ！ 秘薬だから！！\u003c:dt_line_end/\u003e\u003c:th_ch0109/\u003eルビィもらっていい？\u003c:dt_line_end/\u003e\u003c:th_ch0106/\u003eいいわよ、はい\u003c:dt_line_end/\u003e\u003c:th_ch0109/\u003eピーチ味だあ～～～！\u003c:dt_line_end/\u003e\u003c:th_ch0106/\u003eピーチ味って言わないで！ 秘薬なんだってば！！！\u003c:dt_line_end/\u003e"}