{"language":"ja","daily_theater_id":1000032,"year":2020,"month":3,"day":5,"title":"すき、きらい、すき、きらい","detail_text":"\u003c:th_ch0101/\u003e真姫ちゃんはだんだんみかんがすきになる～、すきになる～、すきすきになっちゃう～……\u003c:dt_line_end/\u003e\u003c:th_ch0006/\u003e……人の前で五円玉揺らして何してんのよ……\u003c:dt_line_end/\u003e\u003c:th_ch0101/\u003eあれ？　催眠術、かかってない？　おかしいなあ。梨子ちゃんはかかったのに……\u003c:dt_line_end/\u003e\u003c:th_ch0006/\u003e催眠術なんてかかるわけないじゃない！？\u003c:dt_line_end/\u003e\u003c:th_ch0101/\u003eええ～、そうかなあ。じゃあ、真姫ちゃんが私にやってみて\u003c:dt_line_end/\u003e\u003c:th_ch0006/\u003e……仕方ないわね。じゃあ、この五円玉をよ～く見て……あなたはみかんを見ると話しかけたくなる～、話しかけたくなる～……なーんてね\u003c:dt_line_end/\u003e\u003c:th_ch0101/\u003eみかんさーん！！\u003c:dt_line_end/\u003e\u003c:th_ch0006/\u003eえっ！？　ちょっと……まさか本当にかかってないわよね……？　ねえ！　千歌！！\u003c:dt_line_end/\u003e\u003c:th_ch0101/\u003eみかんさんっ！　いつもいつも！　みかん色が素敵です！　おいしい上に綺麗なんてすごいっ！　大好きですっ！\u003c:dt_line_end/\u003e\u003c:th_ch0006/\u003e千歌ーーー！！？？　もうなんなのよ、意味わかんない！\u003c:dt_line_end/\u003e"}