{"language":"ja","daily_theater_id":1001055,"year":2022,"month":12,"day":23,"title":"東京タワーの日","detail_text":"\u003c:th_ch0107/\u003eうわあー……\u003c:dt_line_end/\u003e\u003c:th_ch0210/\u003eそ、そんなに上を向くと後ろに倒れてしまいますよ、花丸さん\u003c:dt_line_end/\u003e\u003c:th_ch0107/\u003eあ、そうだね。東京タワーを真下から見るの初めてだったから、つい\u003c:dt_line_end/\u003e\u003c:th_ch0210/\u003e確かに、遠くからほうが見慣れてますよね\u003c:dt_line_end/\u003e\u003c:th_ch0107/\u003eうん！ こっちに来るとき、電車の中から見えるとワクワクするんだ〜。こーんな大きなものが作れるなんて、未来ずら〜！\u003c:dt_line_end/\u003e\u003c:th_ch0210/\u003e確かに、当時の技術の粋を結集させて建てられたものなのでしょうね\u003c:dt_line_end/\u003e\u003c:th_ch0107/\u003e当時の技術……？ あっ、そっか！ 東京タワーができたのってものすごく前だもんね！\u003c:dt_line_end/\u003e\u003c:th_ch0210/\u003eふふっ、そうですね。さあ、一番上まで登りますよ！\u003c:dt_line_end/\u003e\u003c:th_ch0107/\u003eうん！ そこからならニジガクが見えるかな？\u003c:dt_line_end/\u003e\u003c:th_ch0210/\u003e探してみましょう！\u003c:dt_line_end/\u003e"}