{"language":"ja","daily_theater_id":1001154,"year":2023,"month":4,"day":1,"title":"エイプリルフール！","detail_text":"\u003c:th_ch0101/\u003e曜ちゃん、曜ちゃん！エイプリルフールのネタ考えてきた？\u003c:dt_line_end/\u003e\u003c:th_ch0105/\u003e考えてきたよ～！千歌ちゃんは？\u003c:dt_line_end/\u003e\u003c:th_ch0101/\u003e考えてきた！あのね「宿題忘れちゃった～！」って梨子ちゃんに泣きつくんだ～♪\u003c:dt_line_end/\u003e\u003c:th_ch0105/\u003eえ、それって……よくあることだし梨子ちゃん驚かないんじゃない？\u003c:dt_line_end/\u003e\u003c:th_ch0101/\u003eふっふっふ……そこを狙ってるんだよ！\u003c:dt_line_end/\u003e\u003c:th_ch0105/\u003eどういうこと？\u003c:dt_line_end/\u003e\u003c:th_ch0101/\u003e私が宿題忘れっちゃったよ～！って泣きついて、うっそー！って言ったら、梨子ちゃんはびっくりする上によかったー！って思えるなんてお得じゃーん！\u003c:dt_line_end/\u003e\u003c:th_ch0105/\u003eなるほど……理あるね\u003c:dt_line_end/\u003e\u003c:th_ch0101/\u003e今日の私は冴えてるんだよ～。ほらほら、見て。宿題だってちゃーんとやってきてるんだ！\u003c:dt_line_end/\u003e\u003c:th_ch0105/\u003eすごいじゃーん！……あれ？こんな宿題出てたっけ？\u003c:dt_line_end/\u003e\u003c:th_ch0101/\u003eえ？\u003c:dt_line_end/\u003e\u003c:th_ch0105/\u003eもしかして千歌ちゃん、問題集のページ間違えてない……？\u003c:dt_line_end/\u003e\u003c:th_ch0101/\u003eえええっ！？うそーーーーーっ！？\u003c:dt_line_end/\u003e\u003c:th_ch0105/\u003eうっそだよ～♪\u003c:dt_line_end/\u003e\u003c:th_ch0101/\u003e曜ちゃーーーーーん！！！！\u003c:dt_line_end/\u003e\u003c:th_ch0105/\u003eあはははっ！\u003c:dt_line_end/\u003e"}